CHANGELOG.md
CMakeLists.txt
LICENSE
MANIFEST.in
README.md
pyproject.toml
setup.py
cmake/libadicConfig.cmake.in
docs/API_REFERENCE.md
docs/DEMO.md
docs/MATHEMATICAL_REFERENCE.md
docs/PRESENTATION.md
docs/USER_GUIDE.md
docs/project/BENCHMARK_RESULTS.md
docs/project/CRYPTOGRAPHIC_PRIME_IMPLEMENTATION.md
docs/project/CRYPTO_FIX_SUMMARY.md
docs/project/INSTALLATION_STEPS.md
docs/project/PIP_QUICKSTART.md
docs/project/PYPI_READY_SUMMARY.md
docs/project/PYTHON_CRYPTO_API.md
docs/project/PYTHON_TESTING_GUIDE.md
docs/project/REID_LI_VERIFICATION_RESULTS.md
docs/project/RELEASE_CHECKLIST.md
docs/project/SECURITY_ANALYSIS.md
docs/project/VALIDATION_REPORT.md
docs/validation/README.md
docs/validation/run_validation.sh
docs/validation/benchmarks/benchmark_libadic.cpp
docs/validation/challenges/challenge_problems.md
docs/validation/results/compute_reid_li_results.cpp
docs/validation/uniqueness/feature_comparison.md
docs/validation/uniqueness/mathematical_proof.md
docs/validation/validation_output/VALIDATION_REPORT.md
docs/validation/validation_output/pari_gp_results.txt
docs/validation/validation_output/reid_li_summary.txt
docs/validation/validation_output/sagemath_results.txt
examples/bsd_verification.py
examples/character_exploration.py
examples/crypto_demo.py
examples/elliptic_curves_demo.py
examples/flt_frey_verification.py
examples/interactive_demo.cpp
examples/padic_crypto_demo.py
examples/precision_management.py
examples/reid_li_complete.py
examples/test_iwasawa_integration.cpp
examples/validate_mathematics.cpp
examples/verify_rh_ops.cpp
extern/pybind11/CMakeLists.txt
extern/pybind11/include/pybind11/attr.h
extern/pybind11/include/pybind11/buffer_info.h
extern/pybind11/include/pybind11/cast.h
extern/pybind11/include/pybind11/chrono.h
extern/pybind11/include/pybind11/common.h
extern/pybind11/include/pybind11/complex.h
extern/pybind11/include/pybind11/critical_section.h
extern/pybind11/include/pybind11/eigen.h
extern/pybind11/include/pybind11/embed.h
