Metadata-Version: 2.4
Name: libadic
Version: 1.0.0
Summary: High-performance p-adic arithmetic library for the Reid-Li criterion
Home-page: https://github.com/IguanAI/libadic
Author: libadic Contributors
Author-email: libadic Contributors <info@iguan.ai>
Maintainer-email: libadic Development Team <info@iguan.ai>
License-Expression: MIT
Project-URL: Homepage, https://github.com/IguanAI/libadic
Project-URL: Documentation, https://github.com/IguanAI/libadic/blob/main/README.md
Project-URL: Repository, https://github.com/IguanAI/libadic.git
Project-URL: Bug Tracker, https://github.com/IguanAI/libadic/issues
Project-URL: Changelog, https://github.com/IguanAI/libadic/blob/main/CHANGELOG.md
Project-URL: API Reference, https://github.com/IguanAI/libadic/blob/main/docs/API_REFERENCE.md
Project-URL: Crypto API, https://github.com/IguanAI/libadic/blob/main/PYTHON_CRYPTO_API.md
Project-URL: Mathematical Reference, https://github.com/IguanAI/libadic/blob/main/docs/MATHEMATICAL_REFERENCE.md
Keywords: p-adic,number theory,mathematics,riemann hypothesis,reid-li,arithmetic,gamma function,L-functions,cryptography,lattice cryptography,quantum resistant,post quantum,elliptic curves,birch swinnerton-dyer
Classifier: Development Status :: 4 - Beta
Classifier: Intended Audience :: Science/Research
Classifier: Topic :: Scientific/Engineering :: Mathematics
Classifier: Programming Language :: Python :: 3
Classifier: Programming Language :: Python :: 3.7
Classifier: Programming Language :: Python :: 3.8
Classifier: Programming Language :: Python :: 3.9
Classifier: Programming Language :: Python :: 3.10
Classifier: Programming Language :: Python :: 3.11
Classifier: Programming Language :: Python :: 3.12
Classifier: Programming Language :: C++
Classifier: Operating System :: OS Independent
Requires-Python: >=3.7
License-File: LICENSE
Requires-Dist: numpy>=1.19.0
Provides-Extra: crypto
Provides-Extra: dev
Requires-Dist: pytest>=6.0; extra == "dev"
Requires-Dist: pytest-cov; extra == "dev"
Requires-Dist: black; extra == "dev"
Requires-Dist: isort; extra == "dev"
Requires-Dist: mypy; extra == "dev"
Requires-Dist: flake8; extra == "dev"
Requires-Dist: twine; extra == "dev"
Requires-Dist: build; extra == "dev"
Requires-Dist: cibuildwheel; extra == "dev"
Provides-Extra: notebooks
Requires-Dist: jupyter; extra == "notebooks"
Requires-Dist: matplotlib; extra == "notebooks"
Requires-Dist: scipy; extra == "notebooks"
Requires-Dist: sympy; extra == "notebooks"
Provides-Extra: docs
Requires-Dist: sphinx>=4.0; extra == "docs"
Requires-Dist: sphinx-rtd-theme; extra == "docs"
Requires-Dist: sphinx-autodoc-typehints; extra == "docs"
Provides-Extra: all
Requires-Dist: jupyter; extra == "all"
Requires-Dist: matplotlib; extra == "all"
Requires-Dist: scipy; extra == "all"
Requires-Dist: sympy; extra == "all"
Requires-Dist: sphinx>=4.0; extra == "all"
Requires-Dist: sphinx-rtd-theme; extra == "all"
Dynamic: author
Dynamic: home-page
Dynamic: license-file
Dynamic: requires-python
